daedal_emailaddressextractor-0.1.4.dist-info/licenses/LICENSE
emailaddressextractor/__init__.py
emailaddressextractor/extractor.py
daedal_emailaddressextractor-0.1.4.dist-info/METADATA
daedal_emailaddressextractor-0.1.4.dist-info/WHEEL
daedal_emailaddressextractor-0.1.4.dist-info/top_level.txt
daedal_emailaddressextractor-0.1.4.dist-info/RECORD
