Metadata-Version: 2.4
Name: daedal-emailaddressextractor
Version: 0.1.4
Summary: Extracts email addresses from MBOX files
Author-email: Deb Mishra <infra@daedal.org>
Project-URL: Homepage, https://github.com/daedalinc/EmailAddressExtractor.git
Classifier: Programming Language :: Python :: 3
Classifier: License :: OSI Approved :: MIT License
Classifier: Operating System :: OS Independent
Requires-Python: >=3.7
License-File: LICENSE
Dynamic: license-file
